opensrane/__init__.py
opensrane/__init__.pyd
opensrane/version.py
opensrane/All/ObjManager.pyd
opensrane/All/__init__.py
opensrane/All/__init__.pyd
opensrane/All/empty.pyd
opensrane/Analyze/ObjManager.pyd
opensrane/Analyze/ScenarioAnalyze.pyd
opensrane/Analyze/_DispSprd.pyd
opensrane/Analyze/_Frag_OutFlow.pyd
opensrane/Analyze/_NodesGroupsVulnerability.pyd
opensrane/Analyze/_PhysicalAssign.pyd
opensrane/Analyze/_PhysicalEffects.pyd
opensrane/Analyze/_Prob_OutFlow.pyd
opensrane/Analyze/_Sampling.pyd
opensrane/Analyze/_ZeroLevel.pyd
opensrane/Analyze/__init__.py
opensrane/Analyze/__init__.pyd
opensrane/Connectors/DS_LOC.pyd
opensrane/Connectors/ObjManager.pyd
opensrane/Connectors/Out_Physic.pyd
opensrane/Connectors/Pb_LOC.pyd
opensrane/Connectors/__init__.py
opensrane/Connectors/__init__.pyd
opensrane/DateAndTime/DateTime.pyd
opensrane/DateAndTime/ObjManager.pyd
opensrane/DateAndTime/__init__.py
opensrane/DateAndTime/__init__.pyd
opensrane/DispersionSpreadModels/BritterMcQuaid.pyd
opensrane/DispersionSpreadModels/GasGaussian.pyd
opensrane/DispersionSpreadModels/LiquidSpread.pyd
opensrane/DispersionSpreadModels/LqdSprdGaussianGasDisp.pyd
opensrane/DispersionSpreadModels/ObjManager.pyd
opensrane/DispersionSpreadModels/_GlobalParameters.pyd
opensrane/DispersionSpreadModels/__init__.py
opensrane/DispersionSpreadModels/__init__.pyd
opensrane/Fragilities/Fragility.pyd
opensrane/Fragilities/ObjManager.pyd
opensrane/Fragilities/Probit.pyd
opensrane/Fragilities/_GlobalParameters.pyd
opensrane/Fragilities/__init__.py
opensrane/Fragilities/__init__.pyd
opensrane/Hazard/ConstIM.pyd
opensrane/Hazard/Earthquake.pyd
opensrane/Hazard/Explosion_TNT.pyd
opensrane/Hazard/ObjManager.pyd
opensrane/Hazard/OnePointExplosion_TNT.pyd
opensrane/Hazard/_GlobalParameters.pyd
opensrane/Hazard/__init__.py
opensrane/Hazard/__init__.pyd
opensrane/Misc/MiscFuncs.pyd
opensrane/Misc/ObjManager.pyd
opensrane/Misc/WarningRecorder.pyd
opensrane/Misc/_NewClass.pyd
opensrane/Misc/__init__.py
opensrane-0.1.6.dist-info/METADATA
opensrane-0.1.6.dist-info/WHEEL
opensrane-0.1.6.dist-info/top_level.txt
opensrane-0.1.6.dist-info/RECORD
